tf_requests/__init__.py
tf_requests/data_utils.py
tf_requests/env_utils.py
tf_requests/get_auto_compose.py
tf_requests/payload_utils.py
tf_requests/request_utils.py
tf_requests/tf_requests.py
tf_requests-0.1.0.dist-info/entry_points.txt
tf_requests-0.1.0.dist-info/WHEEL
tf_requests-0.1.0.dist-info/METADATA
tf_requests-0.1.0.dist-info/licenses/LICENSE
tf_requests-0.1.0.dist-info/RECORD
