Metadata-Version: 2.1
Name: tf-requests
Version: 0.1.0
Summary: A utility script for interacting with the Testing Farm (TF) API in GitLab CI environments.
License: MIT
Author-email: Juanje Ojeda <juanje@redhat.com>
Requires-Python: >=3.9
Requires-Dist: requests>=2.31.0
Requires-Dist: xmltodict>=0.13.0
